{"frames":{"00.png":{"frame":{"x":1,"y":1,"w":164,"h":165},"rotated":false,"trimmed":true,"spriteSourceSize":{"x":3,"y":6,"w":164,"h":165},"sourceSize":{"w":172,"h":172},"pivot":{"x":0.5,"y":0.5}},"01.png":{"frame":{"x":167,"y":1,"w":167,"h":166},"rotated":false,"trimmed":true,"spriteSourceSize":{"x":5,"y":6,"w":167,"h":166},"sourceSize":{"w":172,"h":172},"pivot":{"x":0.5,"y":0.5}},"02.png":{"frame":{"x":1,"y":171,"w":171,"h":168},"rotated":false,"trimmed":true,"spriteSourceSize":{"x":1,"y":4,"w":171,"h":168},"sourceSize":{"w":172,"h":172},"pivot":{"x":0.5,"y":0.5}},"03.png":{"frame":{"x":336,"y":1,"w":168,"h":168},"rotated":false,"trimmed":true,"spriteSourceSize":{"x":4,"y":4,"w":168,"h":168},"sourceSize":{"w":172,"h":172},"pivot":{"x":0.5,"y":0.5}}},"meta":{"app":"http://www.codeandweb.com/texturepacker","version":"1.0","image":"reelImages-1.png?1562835494834","format":"RGBA8888","size":{"w":512,"h":512},"scale":"1","smartupdate":"$TexturePacker:SmartUpdate:c34c9f450e7538ecd776cff9b44111af:1b1eda18062266ee1b2fc85890071e7e:ab49c15c5a4faa9ae4fbcdff94e0308c$"}}